urlpath/__init__.py
urlpath/_compat.py
urlpath/_flavour.py
urlpath/_url.py
urlpath/_utils.py
urlpath-2.0.0.dist-info/METADATA
urlpath-2.0.0.dist-info/WHEEL
urlpath-2.0.0.dist-info/licenses/LICENSE
urlpath-2.0.0.dist-info/RECORD
