Metadata-Version: 2.4
Name: urlpath
Version: 2.0.0
Summary: Object-oriented URL from urllib.parse and pathlib
Project-URL: Homepage, https://github.com/brandonschabell/urlpath
Project-URL: Repository, https://github.com/brandonschabell/urlpath
Project-URL: Issues, https://github.com/brandonschabell/urlpath/issues
Project-URL: Download, https://pypi.org/project/urlpath/
Author-email: Brandon Schabell <brandonschabell@gmail.com>
License-Expression: MIT
License-File: LICENSE
Keywords: http,pathlib,requests,uri,url,urllib
Classifier: Development Status :: 5 - Production/Stable
Classifier: Environment :: Web Environment
Classifier: Intended Audience :: Developers
Classifier: License :: OSI Approved :: MIT License
Classifier: Operating System :: OS Independent
Classifier: Programming Language :: Python :: 3.9
Classifier: Programming Language :: Python :: 3.10
Classifier: Programming Language :: Python :: 3.11
Classifier: Programming Language :: Python :: 3.12
Classifier: Programming Language :: Python :: 3.13
Classifier: Programming Language :: Python :: 3.14
Classifier: Topic :: Internet :: WWW/HTTP
Classifier: Topic :: Software Development :: Libraries :: Python Modules
Requires-Python: >=3.9
Requires-Dist: charset-normalizer<4,>=2
Requires-Dist: requests
Provides-Extra: json
Requires-Dist: jmespath; extra == 'json'
